aftermath/__init__.py
aftermath/engine.py
aftermath/errors.py
aftermath/example.py
aftermath-0.1.0.dist-info/METADATA
aftermath-0.1.0.dist-info/WHEEL
aftermath-0.1.0.dist-info/top_level.txt
aftermath-0.1.0.dist-info/RECORD
